allentools/__init__.py
allentools/basic.py
allentools/config.py
allentools/db.py
allentools/hash.py
allentools/security.py
AllenTools-0.1.1.dist-info/METADATA
AllenTools-0.1.1.dist-info/WHEEL
AllenTools-0.1.1.dist-info/top_level.txt
AllenTools-0.1.1.dist-info/RECORD
